deamen_yaml/__init__.py
deamen_yaml/utils.py
deamen_yaml-0.1.0.dist-info/LICENSE
deamen_yaml-0.1.0.dist-info/METADATA
deamen_yaml-0.1.0.dist-info/WHEEL
deamen_yaml-0.1.0.dist-info/top_level.txt
deamen_yaml-0.1.0.dist-info/RECORD
