Metadata-Version: 2.1
Name: deamen_yaml
Version: 0.1.0
Summary: Frequently used Yaml codes
Author-email: Song Tang <deamen@gmail.com>
License: GPL-3.0-only
Project-URL: Homepage, https://github.com/deamen/python-modules/tree/master/deamen_yaml
Keywords: Yaml,Indent,Indentation
Classifier: Programming Language :: Python :: 3
Classifier: License :: OSI Approved :: GNU General Public License v3 (GPLv3)
Classifier: Operating System :: OS Independent
License-File: LICENSE
Requires-Dist: requests
